sim/des_s_box/des_s_box.v
/**************************************************************************************
*   Name        :des_s_box.v
*   Description :DES des_s_box,part of des_top.v 
*                输入最高位编号1，最低为编号64,其他类似
*   Origin      :20181229
*   Author      :helrori2011@gmail.com
**************************************************************************************/
module des_s_box
(
    input wire  [1:6]address,
    output wire [1:4]sout
);
parameter width     = 4;
parameter widthad   = 6;
parameter datafile  = "none";
reg [width-1:0] mem [(2**widthad)-1:0];
reg[6:0] n;

/*
    CAUTION $readmemh 部分综合工具可能无法综合!
*/
initial
begin
$readmemh(datafile, mem);
$display("datafile : %s ",datafile);
for(n=0;n<64;n=n+1)
	$display("0x%h ",mem[n]);
end

wire [5:0]new_address;
assign new_address = {address[1],address[6],address[2:5]};
assign sout = mem[new_address];

endmodule

sim/des_s_box/des_s_box_tb.v
`timescale 1 ns / 1 ps
module des_s_box_tb();
reg  [1:6]address;
wire [1:4]sout;
initial begin
        $dumpfile("wave.vcd");              //for iverilog gtkwave.exe
        $dumpvars(0,des_s_box_tb);          //for iverilog select signal      
        address = 'b0;
        
        repeat(64)begin
        #5 address = address + 1'd1;    
        end
        #10 $finish;        
end
    
des_s_box #(.datafile("G:/WORK_SPACE/Verilog_HDL_CODE/Data_Encryption_Standard/s_box_1.txt"))
des_s_box_1
(
    .address(address),//6bits
    .sout(sout)//4bits
);

endmodule

sim/des_s_box/wave.vcd
$date
	Mon Dec 31 14:37:04 2018
$end
$version
	Icarus Verilog
$end
$timescale
	1ps
$end
$scope module des_s_box_tb $end
$var wire 4 ! sout [1:4] $end
$var reg 6 " address [1:6] $end
$scope module des_s_box_1 $end
$var wire 6 # address [1:6] $end
$var wire 4 $ sout [1:4] $end
$var wire 6 % new_address [5:0] $end
$var reg 7 & n [6:0] $end
$upscope $end
$upscope $end
$enddefinitions $end
#0
$dumpvars
b1000000 &
b0 %
b1110 $
b0 #
b0 "
b1110 !
$end
#5000
b0 !
b0 $
b10000 %
b1 "
b1 #
#10000
b100 !
b100 $
b1 %
b10 "
b10 #
#15000
b1111 !
b1111 $
b10001 %
b11 "
b11 #
#20000
b1101 !
b1101 $
b10 %
b100 "
b100 #
#25000
b111 !
b111 $
b10010 %
b101 "
b101 #
#30000
b1 !
b1 $
b11 %
b110 "
b110 #
#35000
b100 !
b100 $
b10011 %
b111 "
b111 #
#40000
b10 !
b10 $
b100 %
b1000 "
b1000 #
#45000
b1110 !
b1110 $
b10100 %
b1001 "
b1001 #
#50000
b1111 !
b1111 $
b101 %
b1010 "
b1010 #
#55000
b10 !
b10 $
b10101 %
b1011 "
b1011 #
#60000
b1011 !
b1011 $
b110 %
b1100 "
b1100 #
#65000
b1101 !
b1101 $
b10110 %
b1101 "
b1101 #
#70000
b1000 !
b1000 $
b111 %
b1110 "
b1110 #
#75000
b1 !
b1 $
b10111 %
b1111 "
b1111 #
#80000
b11 !
b11 $
b1000 %
b10000 "
b10000 #
#85000
b1010 !
b1010 $
b11000 %
b10001 "
b10001 #
#90000
b1010 !
b1010 $
b1001 %
b10010 "
b10010 #
#95000
b110 !
b110 $
b11001 %
b10011 "
b10011 #
#100000
b110 !
b110 $
b1010 %
b10100 "
b10100 #
#105000
b1100 !
b1100 $
b11010 %
b10101 "
b10101 #
#110000
b1100 !
b1100 $
b1011 %
b10110 "
b10110 #
#115000
b1011 !
b1011 $
b11011 %
b10111 "
b10111 #
#120000
b101 !
b101 $
b1100 %
b11000 "
b11000 #
#125000
b1001 !
b1001 $
b11100 %
b11001 "
b11001 #
#130000
b1001 !
b1001 $
b1101 %
b11010 "
b11010 #
#135000
b101 !
b101 $
b11101 %
b11011 "
b11011 #
#140000
b0 !
b0 $
b1110 %
b11100 "
b11100 #
#145000
b11 !
b11 $
b11110 %
b11101 "
b11101 #
#150000
b111 !
b111 $
b1111 %
b11110 "
b11110 #
#155000
b1000 !
b1000 $
b11111 %
b11111 "
b11111 #
#160000
b100 !
b100 $
b100000 %
b100000 "
b100000 #
#165000
b1111 !
b1111 $
b110000 %
b100001 "
b100001 #
#170000
b1 !
b1 $
b100001 %
b100010 "
b100010 #
#175000
b1100 !
b1100 $
b110001 %
b100011 "
b100011 #
#180000
b1110 !
b1110 $
b100010 %
b100100 "
b100100 #
#185000
b1000 !
b1000 $
b110010 %
b100101 "
b100101 #
#190000
b1000 !
b1000 $
b100011 %
b100110 "
b100110 #
#195000
b10 !
b10 $
b110011 %
b100111 "
b100111 #
#200000
b1101 !
b1101 $
b100100 %
b101000 "
b101000 #
#205000
b100 !
b100 $
b110100 %
b101001 "
b101001 #
#210000
b110 !
b110 $
b100101 %
b101010 "
b101010 #
#215000
b1001 !
b1001 $
b110101 %
b101011 "
b101011 #
#220000
b10 !
b10 $
b100110 %
b101100 "
b101100 #
#225000
b1 !
b1 $
b110110 %
b101101 "
b101101 #
#230000
b1011 !
b1011 $
b100111 %
b101110 "
b101110 #
#235000
b111 !
b111 $
b110111 %
b101111 "
b101111 #
#240000
b1111 !
b1111 $
b101000 %
b110000 "
b110000 #
#245000
b101 !
b101 $
b111000 %
b110001 "
b110001 #
#250000
b1100 !
b1100 $
b101001 %
b110010 "
b110010 #
#255000
b1011 !
b1011 $
b111001 %
b110011 "
b110011 #
#260000
b1001 !
b1001 $
b101010 %
b110100 "
b110100 #
#265000
b11 !
b11 $
b111010 %
b110101 "
b110101 #
#270000
b111 !
b111 $
b101011 %
b110110 "
b110110 #
#275000
b1110 !
b1110 $
b111011 %
b110111 "
b110111 #
#280000
b11 !
b11 $
b101100 %
b111000 "
b111000 #
#285000
b1010 !
b1010 $
b111100 %
b111001 "
b111001 #
#290000
b1010 !
b1010 $
b101101 %
b111010 "
b111010 #
#295000
b0 !
b0 $
b111101 %
b111011 "
b111011 #
#300000
b101 !
b101 $
b101110 %
b111100 "
b111100 #
#305000
b110 !
b110 $
b111110 %
b111101 "
b111101 #
#310000
b0 !
b0 $
b101111 %
b111110 "
b111110 #
#315000
b1101 !
b1101 $
b111111 %
b111111 "
b111111 #
#320000
b1110 !
b1110 $
b0 %
b0 "
b0 #
