final_rtl/des_pc2.v
/**************************************************************************************
*   Name        :des_pc2.v
*   Description :DES subkeys pc2,part of des_top.v 
*                输入最高位编号1，最低为编号64,其他类似
*   Origin      :20181228
*   Author      :helrori2011@gmail.com
**************************************************************************************/
module des_pc2
(
    input   wire [1:28] li_28,
    input   wire [1:28] ri_28,
    output  wire [1:48] kout_48
);
wire [1:56]in_56;
assign in_56 = {li_28,ri_28};
assign kout_48 = {
in_56[14], in_56[17], in_56[11], in_56[24], in_56[1],  in_56[5], 
in_56[3],  in_56[28], in_56[15], in_56[6],  in_56[21], in_56[10],
in_56[23], in_56[19], in_56[12], in_56[4],  in_56[26], in_56[8], 
in_56[16], in_56[7],  in_56[27], in_56[20], in_56[13], in_56[2],

in_56[41], in_56[52], in_56[31], in_56[37], in_56[47], in_56[55], 
in_56[30], in_56[40], in_56[51], in_56[45], in_56[33], in_56[48], 
in_56[44], in_56[49], in_56[39], in_56[56], in_56[34], in_56[53], 
in_56[46], in_56[42], in_56[50], in_56[36], in_56[29], in_56[32]

};
endmodule

des_subkeys_unit.v
module des_subkeys_unit
(
    input  wire [4:0]cnt_0,
    input  wire encrypt,
    input  wire [1:28]li_28,
    input  wire [1:28]ri_28,
    output wire [1:48]subkeys_48_wire,
    output reg [1:28]lo_28,
    output reg [1:28]ro_28 
);
always@(*)
if(encrypt)
    case(cnt_0)
        5'd0,5'd1,5'd8,5'd15:begin
        lo_28=li_28<<1;
        ro_28=ri_28<<1;
        lo_28[28]=li_28[1];
        ro_28[28]=ri_28[1];
        end
        5'd2,5'd3,5'd4,5'd5,5'd6,5'd7,5'd9,5'd10,5'd11,5'd12,5'd13,5'd14:begin
        lo_28=li_28<<2;
        ro_28=ri_28<<2;
        lo_28[27:28]=li_28[1:2];
        ro_28[27:28]=ri_28[1:2];
        end
//        default:;
    endcase
else 
    case(cnt_0)
        5'd1,5'd8,5'd15:begin
        lo_28=li_28>>1;
        ro_28=ri_28>>1;
        lo_28[1]=li_28[28];
        ro_28[1]=ri_28[28];
        end
        5'd2,5'd3,5'd4,5'd5,5'd6,5'd7,5'd9,5'd10,5'd11,5'd12,5'd13,5'd14:begin
        lo_28=li_28>>2;
        ro_28=ri_28>>2;
        lo_28[1:2]=li_28[27:28];
        ro_28[1:2]=ri_28[27:28];
        end
        5'd0:begin lo_28=li_28;ro_28=ri_28;end
//        default:;
    endcase
des_pc2 des_pc2_1
(
    .li_28(lo_28),
    .ri_28(ro_28),
    .kout_48(subkeys_48_wire)
);
endmodule

quartus_for_gate_sim/rtl/des_pc1.v
/**************************************************************************************
*   Name        :des_pc1.v
*   Description :DES subkeys pc1,part of des_top.v 
*                输入最高位编号1，最低为编号64,其他类似。
*                忽略奇偶校验位,没有8,16,24,32,40,48,56和64
*   Origin      :20181228
*   Author      :helrori2011@gmail.com
**************************************************************************************/
module des_pc1
(
    input   wire [1:64] in_64,
    output  wire [1:28] lo_28,
    output  wire [1:28] ro_28
);
assign {lo_28,ro_28} = {
in_64[57], in_64[49], in_64[41], in_64[33], in_64[25], in_64[17], in_64[9],
in_64[1],  in_64[58], in_64[50], in_64[42], in_64[34], in_64[26], in_64[18], 
in_64[10], in_64[2],  in_64[59], in_64[51], in_64[43], in_64[35], in_64[27], 
in_64[19], in_64[11], in_64[3],  in_64[60], in_64[52], in_64[44], in_64[36], 

in_64[63], in_64[55], in_64[47], in_64[39], in_64[31], in_64[23], in_64[15], 
in_64[7],  in_64[62], in_64[54], in_64[46], in_64[38], in_64[30], in_64[22],
in_64[14], in_64[6],  in_64[61], in_64[53], in_64[45], in_64[37], in_64[29],
in_64[21], in_64[13], in_64[5],  in_64[28], in_64[20], in_64[12], in_64[4]

};
endmodule

sim/des_subkeys_gen/des_subkeys_gen.v
/**************************************************************************************
*   Name        :des_subkeys_gen.v
*   Description :part of des_top.v.多时钟周期，单位结构复用。
*                输入最高位编号1，最低为编号64,其他类似。
*                系统上电后(or 通过key_in_64_en同步更新密码后)执行19个周期提前产生subkeys
*                key_in_64_en __|~~~~~~~~~|___________________________
*                clk          __|~~~~|____|~~~~|____|~~~~|____|~~~~|__
*                key_in_64_buff0_ok ~~~~~~|_________|~~~~~~~~~~~~~~~~~
*                key_in_64_buff0 __________XXXXXXXXXXXXXXXXXXXXXXXXXXX
*                state        ________________________________X  1   X
*   Origin      :20181230
*                20181231
*   Author      :helrori2011@gmail.com
**************************************************************************************/

module des_subkeys_gen
(
    input  wire clk,
    input  wire rst_n,
    
    input  wire key_in_64_en,//1:change the keys;0:always zeros
    input  wire encrypt,//1: encrypt;0: decrypt
    input  wire [1:64]key_in_64,
    output reg  [1:48]subkeys_1,
    output reg  [1:48]subkeys_2,
    output reg  [1:48]subkeys_3,
    output reg  [1:48]subkeys_4,
    output reg  [1:48]subkeys_5,
    output reg  [1:48]subkeys_6,
    output reg  [1:48]subkeys_7,
    output reg  [1:48]subkeys_8,
    output reg  [1:48]subkeys_9,
    output reg  [1:48]subkeys_10,
    output reg  [1:48]subkeys_11,
    output reg  [1:48]subkeys_12,
    output reg  [1:48]subkeys_13,
    output reg  [1:48]subkeys_14,
    output reg  [1:48]subkeys_15,
    output reg  [1:48]subkeys_16,
    output wire subkeys_16_valid,
    output wire parity_check_error
    
);
/*
*   缓冲密码
*   input  key_in_64
*   output key_in_64_buff0,key_in_64_buff0_ok
*/
reg [1:64]key_in_64_buff0;
reg key_in_64_buff0_ok;
assign parity_check_error = ~((^key_in_64_buff0[1:8])&(^key_in_64_buff0[9:16])&(^key_in_64_buff0[17:24])&(^key_in_64_buff0[25:32])
                           &(^key_in_64_buff0[33:40])&(^key_in_64_buff0[41:48])&(^key_in_64_buff0[49:56])&(^key_in_64_buff0[57:64]));
always@(posedge clk or negedge rst_n)begin
    if(!rst_n)begin
        key_in_64_buff0_ok  <= 1'd0;
        key_in_64_buff0     <= 64'd0;//默认64'd0
    end else if(key_in_64_en)begin
        key_in_64_buff0_ok  <= 1'd0;
        key_in_64_buff0     <= key_in_64;
    end else begin
        key_in_64_buff0_ok  <= 1'd1;
        key_in_64_buff0     <= key_in_64_buff0;
    end
end
/*
*   cnt_0 des_subkeys_unit块选
*/
reg [4:0]cnt_0;
reg [1:0]state;
assign subkeys_16_valid = (state == 2'd3);//state == 3为subkeys稳定有效状态,其他状态是生成subkeys过程中
always@(posedge clk or negedge rst_n)begin
    if(!rst_n)begin
        cnt_0 <= 'd0;
        state <= 'd0;
    end else if(key_in_64_buff0_ok)begin//user updated keys
        if(state == 2'd0)begin
            state <= state + 2'd1;
        end else if(state == 2'd1 && cnt_0 < 5'd15)begin
            cnt_0 <= cnt_0 + 1'd1;
        end else if(state == 2'd1)begin//转至空闲state
            state <= state + 2'd1;
            cnt_0 <= 5'd0;
        end else if(state == 2'd2)begin
            state <= state + 2'd1;
        end else state <= state;//subkeys generated
    end else begin//user try to update keys
        state <= 'd0;
        cnt_0 <= 5'd0;
    end
end
wire [1:28]pc1_lo_28,pc1_ro_28,li_28,ri_28,lo_28,ro_28;
wire [1:48]subkeys_48_wire;
reg  [1:28]lo_28_buff,ro_28_buff;
assign li_28 = (cnt_0 == 5'd0)?pc1_lo_28:lo_28_buff;
assign ri_28 = (cnt_0 == 5'd0)?pc1_ro_28:ro_28_buff;
des_pc1 des_pc1_0
(
    .in_64(key_in_64_buff0),
    .lo_28(pc1_lo_28),
    .ro_28(pc1_ro_28)
);
des_subkeys_unit des_subkeys_unit_0
(
    .cnt_0(cnt_0),
    .encrypt(encrypt),
    .li_28(li_28),
    .ri_28(ri_28),
    .subkeys_48_wire(subkeys_48_wire),
    .lo_28(lo_28),
    .ro_28(ro_28)
);
always@(posedge clk or negedge rst_n)begin
if(!rst_n)begin
    lo_28_buff <= 28'd0;
    ro_28_buff <= 28'd0;
end else if(key_in_64_buff0_ok && state == 2'd1)begin
    lo_28_buff<=lo_28;
    ro_28_buff<=ro_28;
    case(cnt_0)
    4'd0:subkeys_1   <= subkeys_48_wire;
    4'd1:subkeys_2   <= subkeys_48_wire;
    4'd2:subkeys_3   <= subkeys_48_wire;
    4'd3:subkeys_4   <= subkeys_48_wire;
    4'd4:subkeys_5   <= subkeys_48_wire;
    4'd5:subkeys_6   <= subkeys_48_wire;
    4'd6:subkeys_7   <= subkeys_48_wire;
    4'd7:subkeys_8   <= subkeys_48_wire;
    4'd8:subkeys_9   <= subkeys_48_wire;
    4'd9:subkeys_10  <= subkeys_48_wire;
    4'd10:subkeys_11 <= subkeys_48_wire;
    4'd11:subkeys_12 <= subkeys_48_wire;
    4'd12:subkeys_13 <= subkeys_48_wire;
    4'd13:subkeys_14 <= subkeys_48_wire;
    4'd14:subkeys_15 <= subkeys_48_wire;
    4'd15:subkeys_16 <= subkeys_48_wire;
    endcase
end
end
endmodule

sim/des_subkeys_gen/des_subkeys_gen_tb.v
`timescale 1 ns / 1 ps
module des_subkeys_gen_tb();
reg clk,rst_n,key_in_64_en,encrypt;
reg [1:64]key_in_64;
wire [1:48]subkeys_1,subkeys_2,subkeys_3,subkeys_4,subkeys_5,subkeys_6,subkeys_7,subkeys_8;
wire [1:48]subkeys_9,subkeys_10,subkeys_11,subkeys_12,subkeys_13,subkeys_14,subkeys_15,subkeys_16;
wire subkeys_16_valid,parity_check_error;
initial begin
        $dumpfile("wave.vcd");              //for iverilog gtkwave.exe
        $dumpvars(0,des_subkeys_gen_tb);          //for iverilog select signal   
        clk = 0;
        rst_n = 1;
        key_in_64_en = 0;
        encrypt = 0;
        key_in_64 = 64'h1334_5779_9BBC_DFF1;
        #20 rst_n=0;
        #20 rst_n=1;
        #10 key_in_64_en = 1;
        #40 key_in_64_en = 0;
//       repeat(128)begin
        #5000
        key_in_64 = 64'hF0F0_0A0A_8888_1111;
        key_in_64_en = 1;
        #20
        key_in_64_en = 0;
        #5000
        rst_n = 0;
        #20
        rst_n = 1;
        #5000
        
//        end
        $finish;
      
end
always begin#10 clk=~clk;end
des_subkeys_gen des_subkeys_gen_0
(
    .clk(clk),
    .rst_n(rst_n),
    .key_in_64_en(key_in_64_en),
    .encrypt(encrypt),
    .key_in_64(key_in_64),
    .subkeys_1(subkeys_1),
    .subkeys_2(subkeys_2),
    .subkeys_3(subkeys_3),
    .subkeys_4(subkeys_4),
    .subkeys_5(subkeys_5),
    .subkeys_6(subkeys_6),
    .subkeys_7(subkeys_7),
    .subkeys_8(subkeys_8),
    .subkeys_9(subkeys_9),
    .subkeys_10(subkeys_10),
    .subkeys_11(subkeys_11),
    .subkeys_12(subkeys_12),
    .subkeys_13(subkeys_13),
    .subkeys_14(subkeys_14),
    .subkeys_15(subkeys_15),
    .subkeys_16(subkeys_16),
    .subkeys_16_valid(subkeys_16_valid),
    .parity_check_error(parity_check_error)
);
endmodule

sim/des_subkeys_gen/wave.vcd
$date
	Mon Dec 31 13:05:34 2018
$end
$version
	Icarus Verilog
$end
$timescale
	1ps
$end
$scope module des_subkeys_gen_tb $end
$var wire 48 ! subkeys_9 [1:48] $end
$var wire 48 " subkeys_8 [1:48] $end
$var wire 48 # subkeys_7 [1:48] $end
$var wire 48 $ subkeys_6 [1:48] $end
$var wire 48 % subkeys_5 [1:48] $end
$var wire 48 & subkeys_4 [1:48] $end
$var wire 48 ' subkeys_3 [1:48] $end
$var wire 48 ( subkeys_2 [1:48] $end
$var wire 1 ) subkeys_16_valid $end
$var wire 48 * subkeys_16 [1:48] $end
$var wire 48 + subkeys_15 [1:48] $end
$var wire 48 , subkeys_14 [1:48] $end
$var wire 48 - subkeys_13 [1:48] $end
$var wire 48 . subkeys_12 [1:48] $end
$var wire 48 / subkeys_11 [1:48] $end
$var wire 48 0 subkeys_10 [1:48] $end
$var wire 48 1 subkeys_1 [1:48] $end
$var wire 1 2 parity_check_error $end
$var reg 1 3 clk $end
$var reg 1 4 encrypt $end
$var reg 64 5 key_in_64 [1:64] $end
$var reg 1 6 key_in_64_en $end
$var reg 1 7 rst_n $end
$scope module des_subkeys_gen_0 $end
$var wire 1 3 clk $end
$var wire 1 4 encrypt $end
$var wire 64 8 key_in_64 [1:64] $end
$var wire 1 6 key_in_64_en $end
$var wire 1 2 parity_check_error $end
$var wire 1 7 rst_n $end
$var wire 48 9 subkeys_48_wire [1:48] $end
$var wire 1 ) subkeys_16_valid $end
$var wire 28 : ro_28 [1:28] $end
$var wire 28 ; ri_28 [1:28] $end
$var wire 28 < pc1_ro_28 [1:28] $end
$var wire 28 = pc1_lo_28 [1:28] $end
$var wire 28 > lo_28 [1:28] $end
$var wire 28 ? li_28 [1:28] $end
$var reg 5 @ cnt_0 [4:0] $end
$var reg 64 A key_in_64_buff0 [1:64] $end
$var reg 1 B key_in_64_buff0_ok $end
$var reg 28 C lo_28_buff [1:28] $end
$var reg 28 D ro_28_buff [1:28] $end
$var reg 2 E state [1:0] $end
$var reg 48 F subkeys_1 [1:48] $end
$var reg 48 G subkeys_10 [1:48] $end
$var reg 48 H subkeys_11 [1:48] $end
$var reg 48 I subkeys_12 [1:48] $end
$var reg 48 J subkeys_13 [1:48] $end
$var reg 48 K subkeys_14 [1:48] $end
$var reg 48 L subkeys_15 [1:48] $end
$var reg 48 M subkeys_16 [1:48] $end
$var reg 48 N subkeys_2 [1:48] $end
$var reg 48 O subkeys_3 [1:48] $end
$var reg 48 P subkeys_4 [1:48] $end
$var reg 48 Q subkeys_5 [1:48] $end
$var reg 48 R subkeys_6 [1:48] $end
$var reg 48 S subkeys_7 [1:48] $end
$var reg 48 T subkeys_8 [1:48] $end
$var reg 48 U subkeys_9 [1:48] $end
$scope module des_pc1_0 $end
$var wire 64 V in_64 [1:64] $end
$var wire 28 W ro_28 [1:28] $end
$var wire 28 X lo_28 [1:28] $end
$upscope $end
$scope module des_subkeys_unit_0 $end
$var wire 5 Y cnt_0 [4:0] $end
$var wire 1 4 encrypt $end
$var wire 28 Z li_28 [1:28] $end
$var wire 28 [ ri_28 [1:28] $end
$var wire 48 \ subkeys_48_wire [1:48] $end
$var reg 28 ] lo_28 [1:28] $end
$var reg 28 ^ ro_28 [1:28] $end
$scope module des_pc2_1 $end
$var wire 28 _ li_28 [1:28] $end
$var wire 28 ` ri_28 [1:28] $end
$var wire 48 a kout_48 [1:48] $end
$var wire 56 b in_56 [1:56] $end
$upscope $end
$upscope $end
$upscope $end
$upscope $end
$enddefinitions $end
#0
$dumpvars
bx b
bx a
bx `
bx _
bx ^
bx ]
bx \
bx [
bx Z
bx Y
bx X
bx W
bx V
bx U
bx T
bx S
bx R
bx Q
bx P
bx O
bx N
bx M
bx L
bx K
bx J
bx I
bx H
bx G
bx F
bx E
bx D
bx C
xB
bx A
bx @
bx ?
bx >
bx =
bx <
bx ;
bx :
bx 9
b1001100110100010101110111100110011011101111001101111111110001 8
17
06
b1001100110100010101110111100110011011101111001101111111110001 5
04
03
x2
bx 1
bx 0
bx /
bx .
bx -
bx ,
bx +
bx *
x)
bx (
bx '
bx &
bx %
bx $
bx #
bx "
bx !
$end
#10000
1B
b0 @
b0 Y
0)
b0 E
13
#20000
b0 9
b0 \
b0 a
b0 :
b0 ^
b0 `
b0 b
b0 >
b0 ]
b0 _
12
b0 ?
b0 Z
b0 ;
b0 [
b0 =
b0 X
b0 <
b0 W
b0 D
b0 C
b0 A
b0 V
0B
03
07
#30000
13
#40000
03
17
#50000
02
b110010110011110110001011000011100001011111110101 9
b110010110011110110001011000011100001011111110101 \
b110010110011110110001011000011100001011111110101 a
b101010101100110011110001111 :
b101010101100110011110001111 ^
b101010101100110011110001111 `
b11110000110011001010101011110101010101100110011110001111 b
b1111000011001100101010101111 >
b1111000011001100101010101111 ]
b1111000011001100101010101111 _
b1111000011001100101010101111 ?
b1111000011001100101010101111 Z
b101010101100110011110001111 ;
b101010101100110011110001111 [
b1111000011001100101010101111 =
b1111000011001100101010101111 X
b101010101100110011110001111 <
b101010101100110011110001111 W
b1001100110100010101110111100110011011101111001101111111110001 A
b1001100110100010101110111100110011011101111001101111111110001 V
13
16
#60000
03
#70000
13
#80000
03
#90000
1B
13
06
#100000
03
#110000
b1 E
13
#120000
03
#130000
b101111111001000110001101001111010011111100001010 9
b101111111001000110001101001111010011111100001010 \
b101111111001000110001101001111010011111100001010 a
b1010101010110011001111000111 :
b1010101010110011001111000111 ^
b1010101010110011001111000111 `
b11111000011001100101010101111010101010110011001111000111 b
b1111100001100110010101010111 >
b1111100001100110010101010111 ]
b1111100001100110010101010111 _
b110010110011110110001011000011100001011111110101 1
b110010110011110110001011000011100001011111110101 F
b101010101100110011110001111 D
b1111000011001100101010101111 C
b1 @
b1 Y
13
#140000
03
#150000
b10111110100001110110111111100101110011100111010 9
b10111110100001110110111111100101110011100111010 \
b10111110100001110110111111100101110011100111010 a
b1110101010101100110011110001 :
b1110101010101100110011110001 ^
b1110101010101100110011110001 `
b11111110000110011001010101011110101010101100110011110001 b
b1111111000011001100101010101 >
b1111111000011001100101010101 ]
b1111111000011001100101010101 _
b1010101010110011001111000111 ;
b1010101010110011001111000111 [
b1111100001100110010101010111 ?
b1111100001100110010101010111 Z
b10 @
b10 Y
b101111111001000110001101001111010011111100001010 (
b101111111001000110001101001111010011111100001010 N
b1010101010110011001111000111 D
b1111100001100110010101010111 C
13
#160000
03
#170000
b100101111100010111010001111110101011101001000001 9
b100101111100010111010001111110101011101001000001 \
b100101111100010111010001111110101011101001000001 a
b1110101010101100110011110001 ;
b1110101010101100110011110001 [
b1111111000011001100101010101 ?
b1111111000011001100101010101 Z
b111101010101011001100111100 :
b111101010101011001100111100 ^
b111101010101011001100111100 `
b1111111100001100110010101010111101010101011001100111100 b
b111111110000110011001010101 >
b111111110000110011001010101 ]
b111111110000110011001010101 _
b10111110100001110110111111100101110011100111010 '
b10111110100001110110111111100101110011100111010 O
b1110101010101100110011110001 D
b1111111000011001100101010101 C
b11 @
b11 Y
13
#180000
03
#190000
b11101010111000111110101100101000110011111101001 9
b11101010111000111110101100101000110011111101001 \
b11101010111000111110101100101000110011111101001 a
b1111010101010110011001111 :
b1111010101010110011001111 ^
b1111010101010110011001111 `
b1011111111000011001100101010001111010101010110011001111 b
b101111111100001100110010101 >
b101111111100001100110010101 ]
b101111111100001100110010101 _
b111101010101011001100111100 ;
b111101010101011001100111100 [
b111111110000110011001010101 ?
b111111110000110011001010101 Z
b100 @
b100 Y
b100101111100010111010001111110101011101001000001 &
b100101111100010111010001111110101011101001000001 P
b111101010101011001100111100 D
b111111110000110011001010101 C
13
#200000
03
#210000
b1000010101111111010011110111101101001110000110 9
b1000010101111111010011110111101101001110000110 \
b1000010101111111010011110111101101001110000110 a
b1100011110101010101100110011 :
b1100011110101010101100110011 ^
b1100011110101010101100110011 `
b1111010101010110011001111 ;
b1111010101010110011001111 [
b101111111100001100110010101 ?
b101111111100001100110010101 Z
b1010111111110000110011001011100011110101010101100110011 b
b101011111111000011001100101 >
b101011111111000011001100101 ]
b101011111111000011001100101 _
b11101010111000111110101100101000110011111101001 %
b11101010111000111110101100101000110011111101001 Q
b1111010101010110011001111 D
b101111111100001100110010101 C
b101 @
b101 Y
13
#220000
03
#230000
b101100011111001101000111101110100100011001001111 9
b101100011111001101000111101110100100011001001111 \
b101100011111001101000111101110100100011001001111 a
b1111000111101010101011001100 :
b1111000111101010101011001100 ^
b1111000111101010101011001100 `
b1010101111111100001100110011111000111101010101011001100 b
b101010111111110000110011001 >
b101010111111110000110011001 ]
b101010111111110000110011001 _
b1100011110101010101100110011 ;
b1100011110101010101100110011 [
b101011111111000011001100101 ?
b101011111111000011001100101 Z
b110 @
b110 Y
b1000010101111111010011110111101101001110000110 $
b1000010101111111010011110111101101001110000110 R
b1100011110101010101100110011 D
b101011111111000011001100101 C
13
#240000
03
#250000
b111000001101101111101011111011011110011110000001 9
b111000001101101111101011111011011110011110000001 \
b111000001101101111101011111011011110011110000001 a
b1111000111101010101011001100 ;
b1111000111101010101011001100 [
b101010111111110000110011001 ?
b101010111111110000110011001 Z
b11110001111010101010110011 :
b11110001111010101010110011 ^
b11110001111010101010110011 `
b1010101011111111000011001100011110001111010101010110011 b
b101010101111111100001100110 >
b101010101111111100001100110 ]
b101010101111111100001100110 _
b101100011111001101000111101110100100011001001111 #
b101100011111001101000111101110100100011001001111 S
b1111000111101010101011001100 D
b101010111111110000110011001 C
b111 @
b111 Y
13
#260000
03
#270000
b111101111000101000111010110000010011101111111011 9
b111101111000101000111010110000010011101111111011 \
b111101111000101000111010110000010011101111111011 a
b1001111000111101010101011001 :
b1001111000111101010101011001 ^
b1001111000111101010101011001 `
b101010101111111100001100111001111000111101010101011001 b
b10101010111111110000110011 >
b10101010111111110000110011 ]
b10101010111111110000110011 _
b11110001111010101010110011 ;
b11110001111010101010110011 [
b101010101111111100001100110 ?
b101010101111111100001100110 Z
b1000 @
b1000 Y
b111000001101101111101011111011011110011110000001 "
b111000001101101111101011111011011110011110000001 T
b11110001111010101010110011 D
b101010101111111100001100110 C
13
#280000
03
#290000
b111011001000010010110111111101100001100010111100 9
b111011001000010010110111111101100001100010111100 \
b111011001000010010110111111101100001100010111100 a
b1001111000111101010101011001 ;
b1001111000111101010101011001 [
b10101010111111110000110011 ?
b10101010111111110000110011 Z
b110011110001111010101010110 :
b110011110001111010101010110 ^
b110011110001111010101010110 `
b11001010101011111111000011000110011110001111010101010110 b
b1100101010101111111100001100 >
b1100101010101111111100001100 ]
b1100101010101111111100001100 _
b111101111000101000111010110000010011101111111011 !
b111101111000101000111010110000010011101111111011 U
b1001111000111101010101011001 D
b10101010111111110000110011 C
b1001 @
b1001 Y
13
#300000
03
#310000
b11000111010010100111110010100000111101100101111 9
b11000111010010100111110010100000111101100101111 \
b11000111010010100111110010100000111101100101111 a
b1001100111100011110101010101 :
b1001100111100011110101010101 ^
b1001100111100011110101010101 `
b110010101010111111110000111001100111100011110101010101 b
b11001010101011111111000011 >
b11001010101011111111000011 ]
b11001010101011111111000011 _
b110011110001111010101010110 ;
b110011110001111010101010110 [
b1100101010101111111100001100 ?
b1100101010101111111100001100 Z
b1010 @
b1010 Y
b111011001000010010110111111101100001100010111100 0
b111011001000010010110111111101100001100010111100 G
b110011110001111010101010110 D
b1100101010101111111100001100 C
13
#320000
03
#330000
b11111001110110000000111111010110101001110101000 9
b11111001110110000000111111010110101001110101000 \
b11111001110110000000111111010110101001110101000 a
b1100110010101010111111110000 >
b1100110010101010111111110000 ]
b1100110010101010111111110000 _
b1001100111100011110101010101 ;
b1001100111100011110101010101 [
b11001010101011111111000011 ?
b11001010101011111111000011 Z
b11001100101010101111111100000110011001111000111101010101 b
b110011001111000111101010101 :
b110011001111000111101010101 ^
b110011001111000111101010101 `
b11000111010010100111110010100000111101100101111 /
b11000111010010100111110010100000111101100101111 H
b1001100111100011110101010101 D
b11001010101011111111000011 C
b1011 @
b1011 Y
13
#340000
03
#350000
b11100101010110111010110110110110011010100011101 9
b11100101010110111010110110110110011010100011101 \
b11100101010110111010110110110110011010100011101 a
b101100110011110001111010101 :
b101100110011110001111010101 ^
b101100110011110001111010101 `
b110011001010101011111111000101100110011110001111010101 b
b11001100101010101111111100 >
b11001100101010101111111100 ]
b11001100101010101111111100 _
b110011001111000111101010101 ;
b110011001111000111101010101 [
b1100110010101010111111110000 ?
b1100110010101010111111110000 Z
b1100 @
b1100 Y
b11111001110110000000111111010110101001110101000 .
b11111001110110000000111111010110101001110101000 I
b110011001111000111101010101 D
b1100110010101010111111110000 C
13
#360000
03
#370000
b10101011111110010001010010000101100111110011001 9
b10101011111110010001010010000101100111110011001 \
b10101011111110010001010010000101100111110011001 a
b110011001010101011111111 >
b110011001010101011111111 ]
b110011001010101011111111 _
b101100110011110001111010101 ;
b101100110011110001111010101 [
b11001100101010101111111100 ?
b11001100101010101111111100 Z
b1100110010101010111111110101011001100111100011110101 b
b101011001100111100011110101 :
b101011001100111100011110101 ^
b101011001100111100011110101 `
b11100101010110111010110110110110011010100011101 -
b11100101010110111010110110110110011010100011101 J
b101100110011110001111010101 D
b11001100101010101111111100 C
b1101 @
b1101 Y
13
#380000
03
#390000
b11110011010111011011001110110111100100111100101 9
b11110011010111011011001110110111100100111100101 \
b11110011010111011011001110110111100100111100101 a
b101010110011001111000111101 :
b101010110011001111000111101 ^
b101010110011001111000111101 `
b11000011001100101010101111110101010110011001111000111101 b
b1100001100110010101010111111 >
b1100001100110010101010111111 ]
b1100001100110010101010111111 _
b101011001100111100011110101 ;
b101011001100111100011110101 [
b110011001010101011111111 ?
b110011001010101011111111 Z
b1110 @
b1110 Y
b10101011111110010001010010000101100111110011001 ,
b10101011111110010001010010000101100111110011001 K
b101011001100111100011110101 D
b110011001010101011111111 C
13
#400000
03
#410000
b110110000001011101111111111000111000001110010 9
b110110000001011101111111111000111000001110010 \
b110110000001011101111111111000111000001110010 a
b101010110011001111000111101 ;
b101010110011001111000111101 [
b1100001100110010101010111111 ?
b1100001100110010101010111111 Z
b1010101011001100111100011110 :
b1010101011001100111100011110 ^
b1010101011001100111100011110 `
b11100001100110010101010111111010101011001100111100011110 b
b1110000110011001010101011111 >
b1110000110011001010101011111 ]
b1110000110011001010101011111 _
b11110011010111011011001110110111100100111100101 +
b11110011010111011011001110110111100100111100101 L
b101010110011001111000111101 D
b1100001100110010101010111111 C
b1111 @
b1111 Y
13
#420000
03
#430000
b110010110011110110001011000011100001011111110101 9
b110010110011110110001011000011100001011111110101 \
b110010110011110110001011000011100001011111110101 a
b101010101100110011110001111 :
b101010101100110011110001111 ^
b101010101100110011110001111 `
b11110000110011001010101011110101010101100110011110001111 b
b1111000011001100101010101111 >
b1111000011001100101010101111 ]
b1111000011001100101010101111 _
b101010101100110011110001111 ;
b101010101100110011110001111 [
b1111000011001100101010101111 ?
b1111000011001100101010101111 Z
b0 @
b0 Y
b10 E
b110110000001011101111111111000111000001110010 *
b110110000001011101111111111000111000001110010 M
b1010101011001100111100011110 D
b1110000110011001010101011111 C
13
#440000
03
#450000
1)
b11 E
13
